cron_parser/__init__.py
cron_parser/cli.py
cron_parser/constants.py
cron_parser/parse_cron_expression.py
cron_parser/process_cron.py
cron_parser/validate_cron.py
cron_parser-2.0.0.dist-info/METADATA
cron_parser-2.0.0.dist-info/WHEEL
cron_parser-2.0.0.dist-info/entry_points.txt
cron_parser-2.0.0.dist-info/top_level.txt
cron_parser-2.0.0.dist-info/RECORD
