Metadata-Version: 2.1
Name: cron-parser
Version: 2.0.0
Summary: Cron expression parser
Author: Pooja Deshmukh
Author-email: pooja.deshmukh7745@gmail.com
Requires-Python: >=3.12
